setup.cfg
setup.py
brGenerator/__init__.py
brGenerator/personGen.py
brGenerator/setup.py
brGenerator.egg-info/PKG-INFO
brGenerator.egg-info/SOURCES.txt
brGenerator.egg-info/dependency_links.txt
brGenerator.egg-info/requires.txt
brGenerator.egg-info/top_level.txt