Metadata-Version: 1.0
Name: brGenerator
Version: 1.2
Summary: Modulo para gerar informações de pessoas, util para automação de cadastros/
Home-page: https://github.com/mthbernardes/brGenerator
Author: Matheus Bernardes
Author-email: mthbernardes@gmail.com
License: MIT License
Keywords: gerador pessoas
Platform: UNKNOWN
